Metadata-Version: 1.1
Name: mutalyzer-client
Version: 0.0.1
Summary: CLI for the Mutalyzer API.
Home-page: https://github.com/mutalyzer/client
Author: Jeroen F.J. Laros
Author-email: J.F.J.Laros@lumc.nl
License: MIT
Platform: UNKNOWN
Classifier: Programming Language :: Python :: 3
Classifier: Programming Language :: Python :: 3.5
